trackf/__init__.py
trackf/ctrack.py
trackf-1.0.0.data/data/LICENSE
trackf-1.0.0.data/scripts/ctrack.py
trackf-1.0.0.dist-info/LICENSE
trackf-1.0.0.dist-info/METADATA
trackf-1.0.0.dist-info/WHEEL
trackf-1.0.0.dist-info/top_level.txt
trackf-1.0.0.dist-info/RECORD
