Metadata-Version: 2.1
Name: trackf
Version: 1.0.0
Summary: tracking polymer chain breakage
Home-page: UNKNOWN
Maintainer: Nattavipa Chongvimansin
Maintainer-email: nchongvi@andrew.cmu.edu
License: GPL
Platform: linux
Requires-Dist: numpy
Requires-Dist: netCDF4
Requires-Dist: matplotlib
Requires-Dist: scipy
